[{"id":9998,"id_city":56,"id_district":607,"name":"X\u00e3 B\u00ecnh L\u1ed9c"},{"id":9999,"id_city":56,"id_district":607,"name":"X\u00e3 Su\u1ed1i Ti\u00ean"},{"id":10000,"id_city":56,"id_district":607,"name":"X\u00e3 Su\u1ed1i Hi\u1ec7p"},{"id":10001,"id_city":56,"id_district":607,"name":"X\u00e3 Di\u00ean Xu\u00e2n"},{"id":10002,"id_city":56,"id_district":607,"name":"X\u00e3 Di\u00ean To\u00e0n"},{"id":10003,"id_city":56,"id_district":607,"name":"X\u00e3 Di\u00ean Th\u1ecd"},{"id":10004,"id_city":56,"id_district":607,"name":"X\u00e3 Di\u00ean Th\u1ea1nh"},{"id":10005,"id_city":56,"id_district":607,"name":"X\u00e3 Di\u00ean T\u00e2n"},{"id":10006,"id_city":56,"id_district":607,"name":"X\u00e3 Di\u00ean S\u01a1n"},{"id":10007,"id_city":56,"id_district":607,"name":"X\u00e3 Di\u00ean Ph\u01b0\u1edbc"},{"id":10008,"id_city":56,"id_district":607,"name":"X\u00e3 Di\u00ean Ph\u00fa"},{"id":10009,"id_city":56,"id_district":607,"name":"X\u00e3 Di\u00ean L\u1ed9c"},{"id":10010,"id_city":56,"id_district":607,"name":"X\u00e3 Di\u00ean L\u00e2m"},{"id":10011,"id_city":56,"id_district":607,"name":"X\u00e3 Di\u00ean L\u1ea1c"},{"id":10012,"id_city":56,"id_district":607,"name":"X\u00e3 Di\u00ean H\u00f2a"},{"id":10013,"id_city":56,"id_district":607,"name":"X\u00e3 Di\u00ean \u0110\u1ed3ng"},{"id":10014,"id_city":56,"id_district":607,"name":"X\u00e3 Di\u00ean \u0110i\u1ec1n"},{"id":10015,"id_city":56,"id_district":607,"name":"X\u00e3 Di\u00ean B\u00ecnh"},{"id":10016,"id_city":56,"id_district":607,"name":"X\u00e3 Di\u00ean An"},{"id":10017,"id_city":56,"id_district":607,"name":"Th\u1ecb tr\u1ea5n Di\u00ean Kh\u00e1nh"}]