[{"id":5066,"id_city":31,"id_district":329,"name":"X\u00e3 Y\u1ebfn S\u01a1n"},{"id":5067,"id_city":31,"id_district":329,"name":"X\u00e3 Y\u00ean D\u01b0\u01a1ng"},{"id":5068,"id_city":31,"id_district":329,"name":"X\u00e3 L\u0129nh To\u1ea1i"},{"id":5069,"id_city":31,"id_district":329,"name":"X\u00e3 Ho\u1ea1t Giang"},{"id":5070,"id_city":31,"id_district":329,"name":"X\u00e3 H\u00e0 Y\u00ean"},{"id":5071,"id_city":31,"id_district":329,"name":"X\u00e3 H\u00e0 Vinh"},{"id":5072,"id_city":31,"id_district":329,"name":"X\u00e3 H\u00e0 V\u00e2n"},{"id":5073,"id_city":31,"id_district":329,"name":"X\u00e3 H\u00e0 To\u1ea1i"},{"id":5074,"id_city":31,"id_district":329,"name":"X\u00e3 H\u00e0 Ti\u1ebfn"},{"id":5075,"id_city":31,"id_district":329,"name":"X\u00e3 H\u00e0 Thanh"},{"id":5076,"id_city":31,"id_district":329,"name":"X\u00e3 H\u00e0 Th\u00e1i"},{"id":5077,"id_city":31,"id_district":329,"name":"X\u00e3 H\u00e0 T\u00e2n"},{"id":5078,"id_city":31,"id_district":329,"name":"X\u00e3 H\u00e0 S\u01a1n"},{"id":5079,"id_city":31,"id_district":329,"name":"X\u00e3 H\u00e0 Ph\u00fa"},{"id":5080,"id_city":31,"id_district":329,"name":"X\u00e3 H\u00e0 Phong"},{"id":5081,"id_city":31,"id_district":329,"name":"X\u00e3 H\u00e0 Ninh"},{"id":5082,"id_city":31,"id_district":329,"name":"X\u00e3 H\u00e0 Ng\u1ecdc"},{"id":5083,"id_city":31,"id_district":329,"name":"X\u00e3 H\u00e0 Long"},{"id":5084,"id_city":31,"id_district":329,"name":"X\u00e3 H\u00e0 L\u0129nh"},{"id":5085,"id_city":31,"id_district":329,"name":"X\u00e3 H\u00e0 L\u00e2m"},{"id":5086,"id_city":31,"id_district":329,"name":"X\u00e3 H\u00e0 Lai"},{"id":5087,"id_city":31,"id_district":329,"name":"X\u00e3 H\u00e0 H\u1ea3i"},{"id":5088,"id_city":31,"id_district":329,"name":"X\u00e3 H\u00e0 Giang"},{"id":5089,"id_city":31,"id_district":329,"name":"X\u00e3 H\u00e0 D\u01b0\u01a1ng"},{"id":5090,"id_city":31,"id_district":329,"name":"X\u00e3 H\u00e0 \u0110\u00f4ng"},{"id":5091,"id_city":31,"id_district":329,"name":"X\u00e3 H\u00e0 Ch\u00e2u"},{"id":5092,"id_city":31,"id_district":329,"name":"X\u00e3 H\u00e0 B\u00ecnh"},{"id":5093,"id_city":31,"id_district":329,"name":"X\u00e3 H\u00e0 B\u1eafc"},{"id":5094,"id_city":31,"id_district":329,"name":"Th\u1ecb tr\u1ea5n H\u00e0 Trung"}]