[{"id":6679,"id_city":36,"id_district":384,"name":"X\u00e3 Y\u00ean S\u01a1n"},{"id":6680,"id_city":36,"id_district":384,"name":"X\u00e3 Y\u00ean L\u01b0\u01a1ng"},{"id":6681,"id_city":36,"id_district":384,"name":"X\u00e3 Y\u00ean L\u00e3ng"},{"id":6682,"id_city":36,"id_district":384,"name":"X\u00e3 V\u00f5 Mi\u1ebfu"},{"id":6683,"id_city":36,"id_district":384,"name":"X\u00e3 V\u0103n Mi\u1ebfu"},{"id":6684,"id_city":36,"id_district":384,"name":"X\u00e3 Tinh Nhu\u1ec7"},{"id":6685,"id_city":36,"id_district":384,"name":"X\u00e3 Th\u01b0\u1ee3ng C\u1eedu"},{"id":6686,"id_city":36,"id_district":384,"name":"X\u00e3 Th\u1ee5c Luy\u1ec7n"},{"id":6687,"id_city":36,"id_district":384,"name":"X\u00e3 Th\u1eafng S\u01a1n"},{"id":6688,"id_city":36,"id_district":384,"name":"X\u00e3 Th\u1ea1ch Kho\u00e1n"},{"id":6689,"id_city":36,"id_district":384,"name":"X\u00e3 T\u1ea5t Th\u1eafng"},{"id":6690,"id_city":36,"id_district":384,"name":"X\u00e3 T\u00e2n Minh"},{"id":6691,"id_city":36,"id_district":384,"name":"X\u00e3 T\u00e2n L\u1eadp"},{"id":6692,"id_city":36,"id_district":384,"name":"X\u00e3 S\u01a1n H\u00f9ng"},{"id":6693,"id_city":36,"id_district":384,"name":"X\u00e3 L\u01b0\u01a1ng Nha"},{"id":6694,"id_city":36,"id_district":384,"name":"X\u00e3 Kh\u1ea3 C\u1eedu"},{"id":6695,"id_city":36,"id_district":384,"name":"X\u00e3 H\u01b0\u01a1ng C\u1ea7n"},{"id":6696,"id_city":36,"id_district":384,"name":"X\u00e3 Gi\u00e1p Lai"},{"id":6697,"id_city":36,"id_district":384,"name":"X\u00e3 \u0110\u00f4ng C\u1eedu"},{"id":6698,"id_city":36,"id_district":384,"name":"X\u00e3 \u0110\u1ecbch Qu\u1ea3"},{"id":6699,"id_city":36,"id_district":384,"name":"X\u00e3 C\u1ef1 Th\u1eafng"},{"id":6700,"id_city":36,"id_district":384,"name":"X\u00e3 C\u1ef1 \u0110\u1ed3ng"},{"id":6701,"id_city":36,"id_district":384,"name":"Th\u1ecb tr\u1ea5n Thanh S\u01a1n"}]