[{"id":262,"id_city":2,"id_district":17,"name":"X\u00e3 Vi\u1ec7t H\u00f2a"},{"id":263,"id_city":2,"id_district":17,"name":"X\u00e3 T\u1ee9 D\u00e2n"},{"id":264,"id_city":2,"id_district":17,"name":"X\u00e3 Thu\u1ea7n H\u01b0ng"},{"id":265,"id_city":2,"id_district":17,"name":"X\u00e3 Th\u00e0nh C\u00f4ng"},{"id":266,"id_city":2,"id_district":17,"name":"X\u00e3 T\u00e2n D\u00e2n"},{"id":267,"id_city":2,"id_district":17,"name":"X\u00e3 T\u00e2n Ch\u00e2u"},{"id":268,"id_city":2,"id_district":17,"name":"X\u00e3 Ph\u00f9ng H\u01b0ng"},{"id":269,"id_city":2,"id_district":17,"name":"X\u00e3 \u00d4ng \u0110\u00ecnh"},{"id":270,"id_city":2,"id_district":17,"name":"X\u00e3 Nhu\u1ebf D\u01b0\u01a1ng"},{"id":271,"id_city":2,"id_district":17,"name":"X\u00e3 Li\u00ean Kh\u00ea"},{"id":272,"id_city":2,"id_district":17,"name":"X\u00e3 H\u1ed3ng Ti\u1ebfn"},{"id":273,"id_city":2,"id_district":17,"name":"X\u00e3 H\u00e0m T\u1eed"},{"id":274,"id_city":2,"id_district":17,"name":"X\u00e3 \u0110\u1ed3ng Ti\u1ebfn"},{"id":275,"id_city":2,"id_district":17,"name":"X\u00e3 \u0110\u00f4ng T\u1ea3o"},{"id":276,"id_city":2,"id_district":17,"name":"X\u00e3 \u0110\u00f4ng Ninh"},{"id":277,"id_city":2,"id_district":17,"name":"X\u00e3 \u0110\u00f4ng K\u1ebft"},{"id":278,"id_city":2,"id_district":17,"name":"X\u00e3 D\u00e2n Ti\u1ebfn"},{"id":279,"id_city":2,"id_district":17,"name":"X\u00e3 \u0110\u1ea1i T\u1eadp"},{"id":280,"id_city":2,"id_district":17,"name":"X\u00e3 \u0110\u1ea1i H\u01b0ng"},{"id":281,"id_city":2,"id_district":17,"name":"X\u00e3 D\u1ea1 Tr\u1ea1ch"},{"id":282,"id_city":2,"id_district":17,"name":"X\u00e3 Ch\u00ed T\u00e2n"},{"id":283,"id_city":2,"id_district":17,"name":"X\u00e3 B\u00ecnh Minh"},{"id":284,"id_city":2,"id_district":17,"name":"X\u00e3 B\u00ecnh Ki\u1ec1u"},{"id":285,"id_city":2,"id_district":17,"name":"X\u00e3 An V\u0129"},{"id":286,"id_city":2,"id_district":17,"name":"Th\u1ecb tr\u1ea5n Kho\u00e1i Ch\u00e2u"}]