[{"id":2388,"id_city":19,"id_district":174,"name":"X\u00e3 V\u00e2n Tr\u00ecnh"},{"id":2389,"id_city":19,"id_district":174,"name":"X\u00e3 Tr\u1ecdng Con"},{"id":2390,"id_city":19,"id_district":174,"name":"X\u00e3 Th\u1ee5y H\u00f9ng"},{"id":2391,"id_city":19,"id_district":174,"name":"X\u00e3 Th\u1ecb Ng\u00e2n"},{"id":2392,"id_city":19,"id_district":174,"name":"X\u00e3 Th\u00e1i C\u01b0\u1eddng"},{"id":2393,"id_city":19,"id_district":174,"name":"X\u00e3 Quang Tr\u1ecdng"},{"id":2394,"id_city":19,"id_district":174,"name":"X\u00e3 Minh Khai"},{"id":2395,"id_city":19,"id_district":174,"name":"X\u00e3 L\u00ea L\u1ee3i"},{"id":2396,"id_city":19,"id_district":174,"name":"X\u00e3 L\u00ea Lai"},{"id":2397,"id_city":19,"id_district":174,"name":"X\u00e3 Kim \u0110\u1ed3ng"},{"id":2398,"id_city":19,"id_district":174,"name":"X\u00e3 \u0110\u1ee9c Xu\u00e2n"},{"id":2399,"id_city":19,"id_district":174,"name":"X\u00e3 \u0110\u1ee9c Th\u00f4ng"},{"id":2400,"id_city":19,"id_district":174,"name":"X\u00e3 \u0110\u1ee9c Long"},{"id":2401,"id_city":19,"id_district":174,"name":"X\u00e3 Danh S\u1ef9"},{"id":2402,"id_city":19,"id_district":174,"name":"X\u00e3 Canh T\u00e2n"},{"id":2403,"id_city":19,"id_district":174,"name":"Th\u1ecb tr\u1ea5n \u0110\u00f4ng Kh\u00ea"}]