[{"id":1977,"id_city":17,"id_district":154,"name":"X\u00e3 Vi\u1ec7t Ti\u1ebfn"},{"id":1978,"id_city":17,"id_district":154,"name":"X\u00e3 V\u00e2n Trung"},{"id":1979,"id_city":17,"id_district":154,"name":"X\u00e3 V\u00e2n H\u00e0"},{"id":1980,"id_city":17,"id_district":154,"name":"X\u00e3 T\u1ef1 L\u1ea1n"},{"id":1981,"id_city":17,"id_district":154,"name":"X\u00e3 Trung S\u01a1n"},{"id":1982,"id_city":17,"id_district":154,"name":"X\u00e3 Ti\u00ean S\u01a1n"},{"id":1983,"id_city":17,"id_district":154,"name":"X\u00e3 Th\u01b0\u1ee3ng Lan"},{"id":1984,"id_city":17,"id_district":154,"name":"X\u00e3 T\u0103ng Ti\u1ebfn"},{"id":1985,"id_city":17,"id_district":154,"name":"X\u00e3 Qu\u1ea3ng Minh"},{"id":1986,"id_city":17,"id_district":154,"name":"X\u00e3 Quang Ch\u00e2u"},{"id":1987,"id_city":17,"id_district":154,"name":"X\u00e3 Ninh S\u01a1n"},{"id":1988,"id_city":17,"id_district":154,"name":"X\u00e3 Ngh\u0129a Trung"},{"id":1989,"id_city":17,"id_district":154,"name":"X\u00e3 Minh \u0110\u1ee9c"},{"id":1990,"id_city":17,"id_district":154,"name":"X\u00e3 H\u01b0\u01a1ng Mai"},{"id":1991,"id_city":17,"id_district":154,"name":"X\u00e3 H\u1ed3ng Th\u00e1i"},{"id":1992,"id_city":17,"id_district":154,"name":"X\u00e3 Ho\u00e0ng Ninh"},{"id":1993,"id_city":17,"id_district":154,"name":"X\u00e3 B\u00edch S\u01a1n"},{"id":1994,"id_city":17,"id_district":154,"name":"Th\u1ecb tr\u1ea5n N\u1ebfnh"},{"id":1995,"id_city":17,"id_district":154,"name":"Th\u1ecb tr\u1ea5n B\u00edch \u0110\u1ed9ng"}]