[{"id":7670,"id_city":40,"id_district":424,"name":"X\u00e3 Y\u1ebft Ki\u00eau"},{"id":7671,"id_city":40,"id_district":424,"name":"X\u00e3 Tr\u00f9ng Kh\u00e1nh"},{"id":7672,"id_city":40,"id_district":424,"name":"X\u00e3 To\u00e0n Th\u1eafng"},{"id":7673,"id_city":40,"id_district":424,"name":"X\u00e3 Th\u1ed1ng Nh\u1ea5t"},{"id":7674,"id_city":40,"id_district":424,"name":"X\u00e3 Th\u1ed1ng K\u00eanh"},{"id":7675,"id_city":40,"id_district":424,"name":"X\u00e3 T\u00e2n Ti\u1ebfn"},{"id":7676,"id_city":40,"id_district":424,"name":"X\u00e3 Quang Minh"},{"id":7677,"id_city":40,"id_district":424,"name":"X\u00e3 Ph\u01b0\u01a1ng H\u01b0ng"},{"id":7678,"id_city":40,"id_district":424,"name":"X\u00e3 Ph\u1ea1m Tr\u1ea5n"},{"id":7679,"id_city":40,"id_district":424,"name":"X\u00e3 Nh\u1eadt T\u00e2n"},{"id":7680,"id_city":40,"id_district":424,"name":"X\u00e3 Li\u00ean H\u1ed3ng"},{"id":7681,"id_city":40,"id_district":424,"name":"X\u00e3 L\u00ea L\u1ee3i"},{"id":7682,"id_city":40,"id_district":424,"name":"X\u00e3 H\u1ed3ng H\u01b0ng"},{"id":7683,"id_city":40,"id_district":424,"name":"X\u00e3 Ho\u00e0ng Di\u1ec7u"},{"id":7684,"id_city":40,"id_district":424,"name":"X\u00e3 Gia Xuy\u00ean"},{"id":7685,"id_city":40,"id_district":424,"name":"X\u00e3 Gia T\u00e2n"},{"id":7686,"id_city":40,"id_district":424,"name":"X\u00e3 Gia L\u01b0\u01a1ng"},{"id":7687,"id_city":40,"id_district":424,"name":"X\u00e3 Gia Kh\u00e1nh"},{"id":7688,"id_city":40,"id_district":424,"name":"X\u00e3 Gia H\u00f2a"},{"id":7689,"id_city":40,"id_district":424,"name":"X\u00e3 \u0110\u1ee9c X\u01b0\u01a1ng"},{"id":7690,"id_city":40,"id_district":424,"name":"X\u00e3 \u0110\u1ed3ng Quang"},{"id":7691,"id_city":40,"id_district":424,"name":"X\u00e3 \u0110o\u00e0n Th\u01b0\u1ee3ng"},{"id":7692,"id_city":40,"id_district":424,"name":"Th\u1ecb tr\u1ea5n Gia L\u1ed9c"}]